voxbloxpy/__init__.py
voxbloxpy/_voxbloxpy.cpython-39-x86_64-linux-gnu.so
voxbloxpy/core.py
voxbloxpy/py.typed
voxbloxpy/ros.py
voxbloxpy-0.0.3.dist-info/LICENSE
voxbloxpy-0.0.3.dist-info/METADATA
voxbloxpy-0.0.3.dist-info/WHEEL
voxbloxpy-0.0.3.dist-info/top_level.txt
voxbloxpy-0.0.3.dist-info/RECORD
